[
    {
        "title": "ポテンシャル",
        "url": "potential.html",
        "keywords": "ポテンシャル, ぽてんしゃる, potenital"
    },
    {
        "title": "体積",
        "url": "volume.html",
        "keywords": "体積, volume, 行列式, たいせき, ぎょうれつしき, determinant"
    },
    {
        "title": "直交性欠陥",
        "url": "orthogonality-defect.html",
        "keywords": "直交性欠陥, ちょっこうせいけっかん, orthogonality defect"
    },
    {
        "title": "LLL基底簡約",
        "url": "lll.html",
        "keywords": "LLL基底簡約, LLL簡約, Lenstra-Lenstra-Lovasz基底簡約, LLL-reduction"
    },
    {
        "title": "幾何級数仮定",
        "url": "gsa.html",
        "keywords": "幾何級数仮定, きかきゅうすうかてい, gsa, geometry series assumption"
    },
    {
        "title": "Hermiteの定数",
        "url": "hermite-const.html",
        "keywords": "Hermiteの定数, エルミートの定数, Hermite's constant, えるみーとのていすう"
    },
    {
        "title": "DeepLLL基底簡約",
        "url": "deeplll.html",
        "keywords": "DeepLLL基底簡約, LLL with deep-insertion, DeepLLL-reduction"
    },
    {
        "title": "deep-insertion",
        "url": "deep-insertion.html",
        "keywords": "deep-insertion, deep insertion"
    }
]